{"Data":[{"Number":"8/04.10.2018","Hash":"MuSYv3tfWfM=","DocumentTypeName":"Разрешение за строеж","Status":"Влязъл в сила","TakeEffectFilter":"\/Date(1540242000000)\/","TakeEffect":{"DateTime":"\/Date(1540242000000)\/","FilterText":null},"Issuer":"Главен архитект на СО - р-н \"Илинден\"","Employer":"\"НЕГ\" ЕООД","Object":"Преустройство и промяна предназначение на магазин за промишлени стоки в салон за красота","Region":"Илинден","Terrain":"\"ВЪЛЧО ИВАНОВ - СЕВЕР\"","RegulationNeighbourhood":"858","Upi":"І","Identifier":"68134.1201.67.3.180","Address":"гр. София, кв. \"Света Троица\", бл. 173, вх. В"},{"Number":"72/04.10.2018","Hash":"n7yTNUi1uzI=","DocumentTypeName":"Разрешение за строеж","Status":"Влязъл в сила","TakeEffectFilter":"\/Date(1539982800000)\/","TakeEffect":{"DateTime":"\/Date(1539982800000)\/","FilterText":null},"Issuer":"Главен архитект на СО - р-н \"Овча купел\"","Employer":"Пламен Панов, Дамян Долев, Георги Мирков","Object":"СЕЛСКОСТОПАНСКА СГРАДА","Region":"Овча купел","Terrain":"КУРТОВ ВАЛОГ","RegulationNeighbourhood":null,"Upi":null,"Identifier":"68134.3982.268","Address":""},{"Number":"71/04.10.2018","Hash":"tRUx101Fc8Q=","DocumentTypeName":"Разрешение за строеж","Status":"Влязъл в сила","TakeEffectFilter":"\/Date(1539982800000)\/","TakeEffect":{"DateTime":"\/Date(1539982800000)\/","FilterText":null},"Issuer":"Главен архитект на СО - р-н \"Овча купел\"","Employer":"Искра  Дарджонова, Ясен  Димитров, Стефан Дарджонов, Ангелина Гелкова -Дарджонова","Object":"ЖИЛИЩНА СГРАДА","Region":"Овча купел","Terrain":"м. \"кв. Горна баня\"","RegulationNeighbourhood":"34","Upi":"VІІІ - 8701","Identifier":"68134.4327.8701","Address":"гр. София, ул. \"Гладиола\", кв. кв. Горна баня"},{"Number":"250/03.10.2018","Hash":"tBVUxbnsBU0=","DocumentTypeName":"Разрешение за строеж","Status":"Влязъл в сила","TakeEffectFilter":"\/Date(1541541600000)\/","TakeEffect":{"DateTime":"\/Date(1541541600000)\/","FilterText":null},"Issuer":"Главен архитект на Столична община","Employer":"\"Кантора София\" ЕООД, Димитър  Минков","Object":"Преустройство на пети /тавански етаж/, основен ремонт на покрив и смяна предназначението на офисни помещения в ателие, в пететажна сграда","Region":"Средец","Terrain":"\"ГГЦ ЗОНА Г6\"","RegulationNeighbourhood":"392","Upi":"Х-91","Identifier":"68134.101.91.1","Address":"гр. София, ул. \"Христо Белчев\" № 18"},{"Number":"28/03.10.2018","Hash":"EtyesFEgqck=","DocumentTypeName":"Разрешение за строеж","Status":"Влязъл в сила","TakeEffectFilter":"\/Date(1540155600000)\/","TakeEffect":{"DateTime":"\/Date(1540155600000)\/","FilterText":null},"Issuer":"Главен архитект на СО - р-н \"Искър\"","Employer":"СО район \"Искър\" с кмет Ивайло Цеков","Object":"Площадка за игра на открито","Region":"Искър","Terrain":"\"ДРУЖБА - 1 Ч.\"","RegulationNeighbourhood":"81","Upi":"VI","Identifier":"68134.1500.284","Address":"кв. \"Канала\""},{"Number":"249/02.10.2018","Hash":"gIfD-mOS028=","DocumentTypeName":"Разрешение за строеж","Status":"Влязъл в сила","TakeEffectFilter":"\/Date(1541023200000)\/","TakeEffect":{"DateTime":"\/Date(1541023200000)\/","FilterText":null},"Issuer":"Главен архитект на Столична община","Employer":"Татяна Павлова","Object":"Жилищна сграда","Region":"Надежда","Terrain":"НАДЕЖДА - 2Б","RegulationNeighbourhood":"72","Upi":"XVI - 588","Identifier":"68134.1383.588","Address":""},{"Number":"10/02.10.2018","Hash":"xKvwj-gnDnY=","DocumentTypeName":"Разрешение за строеж","Status":"Влязъл в сила","TakeEffectFilter":"\/Date(1540155600000)\/","TakeEffect":{"DateTime":"\/Date(1540155600000)\/","FilterText":null},"Issuer":"Главен архитект на СО - р-н \"Красна поляна\"","Employer":"Ралица Георгиева","Object":"Двуетажна жилищна сграда с гараж","Region":"Красна поляна","Terrain":"СМЪРДАНА","RegulationNeighbourhood":null,"Upi":null,"Identifier":"68134.1102.50","Address":"гр. София, ул. \"Фортов път\" № 6, кв. м. Смърдана"},{"Number":"68/02.10.2018","Hash":"DRXj3bxq8n8=","DocumentTypeName":"Разрешение за строеж","Status":"Влязъл в сила","TakeEffectFilter":"\/Date(1540414800000)\/","TakeEffect":{"DateTime":"\/Date(1540414800000)\/","FilterText":null},"Issuer":"Главен архитект на СО - р-н \"Връбница\"","Employer":"Илка Варадинова","Object":"Жилищна сграда М/Г+4 с подземни гаражи с К.к 15м","Region":"Връбница","Terrain":"ж.к. \"Обеля-1\"","RegulationNeighbourhood":"44","Upi":"V-1924","Identifier":"68134.2818.1924","Address":""},{"Number":"248/02.10.2018","Hash":"3W780P7_eog=","DocumentTypeName":"Разрешение за строеж","Status":"Влязъл в сила","TakeEffectFilter":"\/Date(1541109600000)\/","TakeEffect":{"DateTime":"\/Date(1541109600000)\/","FilterText":null},"Issuer":"Главен архитект на Столична община","Employer":"\"ЕЙКЪРС ИНВЕСТ\" АД","Object":"Високоетажна жилищна сграда с подземен гараж и допълващо застрояване","Region":"Възраждане","Terrain":"ЗОНА Б -19","RegulationNeighbourhood":"278Б","Upi":"IV ","Identifier":"68134.306.400","Address":""},{"Number":"70/02.10.2018","Hash":"3gATNamgDrI=","DocumentTypeName":"Разрешение за строеж","Status":"Влязъл в сила","TakeEffectFilter":"\/Date(1539810000000)\/","TakeEffect":{"DateTime":"\/Date(1539810000000)\/","FilterText":null},"Issuer":"Главен архитект на СО - р-н \"Овча купел\"","Employer":"Йордан Николов, Росица Николова","Object":"ПРИСТРОЙКА КЪМ ЖИЛИЩНА СГРАДА","Region":"Овча купел","Terrain":"м. в.з.Горна баня","RegulationNeighbourhood":"10","Upi":"I - 546","Identifier":"68134.4330.546.1","Address":"гр. София, ул. \"Пладнище\" № 27"},{"Number":"69/28.09.2018","Hash":"kGwRKMHEeCc=","DocumentTypeName":"Разрешение за строеж","Status":"Влязъл в сила","TakeEffectFilter":"\/Date(1539810000000)\/","TakeEffect":{"DateTime":"\/Date(1539810000000)\/","FilterText":null},"Issuer":"Главен архитект на СО - р-н \"Овча купел\"","Employer":"Румен Соколов, Димитрула Зупиди","Object":"ПРОМЯНА НА ПРЕДНАЗНАЧЕНИЕ НА ТЪРГОВСКИ КАНТОРИ В МЕДИЦИНСКИ ЦЕНТЪР С ФИЗИОТЕРАПИЯ И РЕХАБИЛИТАЦИЯ","Region":"Овча купел","Terrain":"м. \"ж.к. Овча купел 1\"","RegulationNeighbourhood":"104","Upi":"ІV","Identifier":"68134.4333.2007.2","Address":"гр. София, ул. Монтевидео\" № 45"},{"Number":"68/28.09.2018","Hash":"pQf54frciZk=","DocumentTypeName":"Разрешение за строеж","Status":"Влязъл в сила","TakeEffectFilter":"\/Date(1539810000000)\/","TakeEffect":{"DateTime":"\/Date(1539810000000)\/","FilterText":null},"Issuer":"Главен архитект на СО - р-н \"Овча купел\"","Employer":"Румен Соколов, Димитрула Зупиди","Object":"ПРОМЯНА НА ПРЕДНАЗНАЧЕНИЕТО НА ЦЕНТЪР ЗА НЕКОНВЕНЦИОНАЛНИ МЕТОДИ ЗА БЛАГОРОДНО ВЛИЯНИЕ ВЪРХУ ИНДИВИДУАЛНОТО ЗДРАВЕ, ФРИЗЬОРСТВО, МАНИКЮР И КОЗМЕТИКА В МЕДИЦИНСКИ ЦЕНТЪР","Region":"Овча купел","Terrain":"м. \"ж.к. Овча купел 1\"","RegulationNeighbourhood":"104","Upi":"ІV","Identifier":"68134.4333.2007.2","Address":"гр. София, ул. Монтевидео\" № 45"},{"Number":"247/28.09.2018","Hash":"ocMM9e9Wy_s=","DocumentTypeName":"Разрешение за строеж","Status":"Влязъл в сила","TakeEffectFilter":"\/Date(1539896400000)\/","TakeEffect":{"DateTime":"\/Date(1539896400000)\/","FilterText":null},"Issuer":"Главен архитект на Столична община","Employer":"Веселина Ангелова, Михаил  Янков","Object":"Многофамилна жилищна сграда с ателиета и подземен гараж","Region":"Лозенец","Terrain":"М. НПЗ \"ХЛАДИЛНИКА-ВИТОША\", ЧАСТИ СЕВЕР И ЮГ","RegulationNeighbourhood":"9","Upi":"V - 264 \"за ЖС и ОДО\"","Identifier":"68134.903.264","Address":""},{"Number":"67/28.09.2018","Hash":"NmRHWOADhXU=","DocumentTypeName":"Разрешение за строеж","Status":"Влязъл в сила","TakeEffectFilter":"\/Date(1539723600000)\/","TakeEffect":{"DateTime":"\/Date(1539723600000)\/","FilterText":null},"Issuer":"Главен архитект на СО - р-н \"Овча купел\"","Employer":"Живко Сурчев","Object":"НАДСТРОЙКА НАД СЪЩЕСТВУВАЩ ГАРАЖ КЪМ ЖИЛИЩНА СГРАДА ЗА ЗИМНА ГРАДИНА","Region":"Овча купел","Terrain":"м. \"кв. Овча купел - актуализация\"","RegulationNeighbourhood":"13 г","Upi":"ХІІІ - 1215","Identifier":"68134.4337.1215.1","Address":"гр. София, ул. \"Брезов рид\" № 4"},{"Number":"102/28.09.2018","Hash":"-M08nUNKoBI=","DocumentTypeName":"Разрешение за строеж","Status":"Влязъл в сила","TakeEffectFilter":"\/Date(1539723600000)\/","TakeEffect":{"DateTime":"\/Date(1539723600000)\/","FilterText":null},"Issuer":"Главен архитект на СО - р-н \"Лозенец\"","Employer":"ИБЕРИН ЕООД","Object":"ПРЕУСТРОЙСТВО И РЕКОНСТРУКЦИЯ НА СЪЩЕСТВУВАЩА ЖИЛИЩНА СГРАДА","Region":"Лозенец","Terrain":"\"ЛОЗЕНЕЦ III ЧАСТ\"","RegulationNeighbourhood":"62","Upi":"XIII-290","Identifier":"кв. Долни Лозенец - 2-ри етап","Address":"гр. София, ул. Драган Цанков № 18"},{"Number":"101/28.09.2018","Hash":"EFqFqsy7C5g=","DocumentTypeName":"Разрешение за строеж","Status":"Влязъл в сила","TakeEffectFilter":"\/Date(1539637200000)\/","TakeEffect":{"DateTime":"\/Date(1539637200000)\/","FilterText":null},"Issuer":"Главен архитект на СО - р-н \"Лозенец\"","Employer":"Район \"Лозенец\" - СО","Object":"РЕКОНСТРУКЦИЯ НА ДЕТСКА ПЛОЩАДКА В МЕЖДУБЛОКОВО ПРОСТРАНСТВО","Region":"Лозенец","Terrain":"ЛОЗЕНЕЦ II-РА ЧАСТ","RegulationNeighbourhood":"209","Upi":"За ЖС и трафопост","Identifier":"Кв. Горни Лозенец 2-ри етап","Address":"гр. София, ул. междублоково пространство между ул. \"Драгалевска\" и ул. \"Карамашев\" при бл. 8-14"},{"Number":"246/27.09.2018","Hash":"YuqzO6D9PRc=","DocumentTypeName":"Разрешение за строеж","Status":"Влязъл в сила","TakeEffectFilter":"\/Date(1540764000000)\/","TakeEffect":{"DateTime":"\/Date(1540764000000)\/","FilterText":null},"Issuer":"Главен архитект на Столична община","Employer":"\"АДВА-ЕС\" ООД","Object":"Жилищна сграда с ателиета, апартхотел, подземен паркинг с гаражи и наземни паркоместа, СВО и СКО","Region":"Сердика","Terrain":"\"ГГЦ ЗОНА В-15\"","RegulationNeighbourhood":"45","Upi":"XXI - 24,25","Identifier":"68134.514.515","Address":"гр. София, ул. Тимок № 37"},{"Number":"245/27.09.2018","Hash":"FpeJc_BhX20=","DocumentTypeName":"Разрешение за строеж","Status":"Влязъл в сила","TakeEffectFilter":"\/Date(1540242000000)\/","TakeEffect":{"DateTime":"\/Date(1540242000000)\/","FilterText":null},"Issuer":"Главен архитект на Столична община","Employer":"\"Грийнлайф Дружба\" ЕООД","Object":"ЖИЛИЩНА СГРАДА С ПОДЗЕМНИ ГАРАЖИ","Region":"Искър","Terrain":"М.\"ДРУЖБА-РАЗШИРЕНИЕ\" (УЛ.ОБИКОЛНА)","RegulationNeighbourhood":"505","Upi":"IX - 1391 - \"За жилища, обществено обслужване, магазини и ПГ\"","Identifier":"68134.1504.2427","Address":"ул. обиколна"},{"Number":"244/27.09.2018","Hash":"kjs7HYAY4fM=","DocumentTypeName":"Разрешение за строеж","Status":"Влязъл в сила","TakeEffectFilter":"\/Date(1540936800000)\/","TakeEffect":{"DateTime":"\/Date(1540936800000)\/","FilterText":null},"Issuer":"Главен архитект на Столична община","Employer":"\"ЛУКС ИМОТИ\" ООД, \"ПиМ КОНСУЛТИНГ\" ООД","Object":"ЖИЛИЩНА СГРАДА С МАГАЗИНИ М/М+5/М+7 И ПОДЗЕМЕН ГАРАЖ","Region":"Лозенец","Terrain":"М. КРЪСТОВА ВОДА","RegulationNeighbourhood":"9","Upi":"II - 3264, 3289 - \"за ЖС и ОО\"","Identifier":"68134.904.3351","Address":""},{"Number":"243/27.09.2018","Hash":"qgeyFssdfIM=","DocumentTypeName":"Разрешение за строеж","Status":"Влязъл в сила","TakeEffectFilter":"\/Date(1539896400000)\/","TakeEffect":{"DateTime":"\/Date(1539896400000)\/","FilterText":null},"Issuer":"Главен архитект на Столична община","Employer":"\"ПРИМ БГ\" ЕАД","Object":"Изкопни работи и укрепителни мероприятия","Region":"Красно село","Terrain":"СЛАВИЯ","RegulationNeighbourhood":"11","Upi":"III-1890, за ЖС, ОО, подз. гаражи и трафопост","Identifier":"68134.208.1890","Address":""},{"Number":"67/27.09.2018","Hash":"36tcElsaW2Q=","DocumentTypeName":"Разрешение за строеж","Status":"Влязъл в сила","TakeEffectFilter":"\/Date(1539810000000)\/","TakeEffect":{"DateTime":"\/Date(1539810000000)\/","FilterText":null},"Issuer":"Главен архитект на СО - р-н \"Връбница\"","Employer":"\"РАЙТ КЛИЙНИНГ\" ООД с управител Радослав Александров Павлов","Object":"Обществено-обслужваща сграда - офиси, складове, магазини и работилница\"","Region":"Връбница","Terrain":"Волуяк - гарата","RegulationNeighbourhood":"91а","Upi":"II-17","Identifier":"12084.2755.17","Address":""},{"Number":"66/27.09.2018","Hash":"aBVmzhogry0=","DocumentTypeName":"Разрешение за строеж","Status":"Влязъл в сила","TakeEffectFilter":"\/Date(1539810000000)\/","TakeEffect":{"DateTime":"\/Date(1539810000000)\/","FilterText":null},"Issuer":"Главен архитект на СО - р-н \"Връбница\"","Employer":"Христо  Андонов","Object":"Еднофамилна жилищна сграда с изгребна яма","Region":"Връбница","Terrain":"ВОЛУЯК-ГАРАТА","RegulationNeighbourhood":"113","Upi":"XI-1069","Identifier":"12084.2701.2813","Address":"с. Волуяк, ул. 51-ва № 10"},{"Number":"241/26.09.2018","Hash":"bzLGmwJQDEA=","DocumentTypeName":"Разрешение за строеж","Status":"Влязъл в сила","TakeEffectFilter":"\/Date(1537909200000)\/","TakeEffect":{"DateTime":"\/Date(1537909200000)\/","FilterText":null},"Issuer":"Главен архитект на Столична община","Employer":"\"Кадиев и Кадиев\" АД","Object":"Пристройка към съществуваща производствена сграда - довършителни работи","Region":"Надежда","Terrain":"НАДЕЖДА 2А И 2Б ЧАСТ","RegulationNeighbourhood":"73","Upi":"VIII за общ.обсл.","Identifier":"68134.1383.800","Address":""},{"Number":"27/26.09.2018","Hash":"BybmAfGaZzE=","DocumentTypeName":"Разрешение за строеж","Status":"Влязъл в сила","TakeEffectFilter":"\/Date(1539550800000)\/","TakeEffect":{"DateTime":"\/Date(1539550800000)\/","FilterText":null},"Issuer":"Главен архитект на СО - р-н \"Искър\"","Employer":"Костадинка Милошова, Йордан Василев","Object":"Двуфамилна жилищна сграда","Region":"Искър","Terrain":"С. БУСМАНЦИ","RegulationNeighbourhood":"19а","Upi":"VII-470","Identifier":"07106.1419.470","Address":"с. Бусманци"},{"Number":"240/26.09.2018","Hash":"7bOer_KLKtg=","DocumentTypeName":"Разрешение за строеж","Status":"Влязъл в сила","TakeEffectFilter":"\/Date(1539637200000)\/","TakeEffect":{"DateTime":"\/Date(1539637200000)\/","FilterText":null},"Issuer":"Главен архитект на Столична община","Employer":"\"ЛИДЛ България ЕООД енд КО\" КД","Object":"СУПЕРМАРКЕТ \"ЛИДЛ\" С ПОМЕЩЕНИЕ ЗА ПОДГОТОВКА НА ХЛЯБ, ХЛЕБНИ  ИЗДЕЛИЯ И ОТКРИТ ПАРКИНГ","Region":"Оборище","Terrain":null,"RegulationNeighbourhood":"714","Upi":"I - 1 - \"За магазин и ТП\"","Identifier":"68134.404.1","Address":""},{"Number":"239/26.09.2018","Hash":"GJIPntALiso=","DocumentTypeName":"Разрешение за строеж","Status":"Влязъл в сила","TakeEffectFilter":"\/Date(1540155600000)\/","TakeEffect":{"DateTime":"\/Date(1540155600000)\/","FilterText":null},"Issuer":"Главен архитект на Столична община","Employer":"\"ЗЪРНОМЕКС\" ЕООД","Object":"Апартаментен хотел с магазини, подземен гараж и допълващо застрояване - покрита рампа и плътна ограда с H=2,20м. изцяло в границите на имота към странична регулация","Region":"Лозенец","Terrain":"М. НПЗ \"ХЛАДИЛНИКА-ВИТОША\", ЧАСТИ СЕВЕР И ЮГ","RegulationNeighbourhood":"1","Upi":"XVIII - 1158 - \"За апартаментен хотел и магазини\"","Identifier":"68134.903.3264","Address":""},{"Number":"238/25.09.2018","Hash":"4Z8uNo57m2k=","DocumentTypeName":"Разрешение за строеж","Status":"Влязъл в сила","TakeEffectFilter":"\/Date(1540328400000)\/","TakeEffect":{"DateTime":"\/Date(1540328400000)\/","FilterText":null},"Issuer":"Главен архитект на Столична община","Employer":"\"К и М- Стил\" ЕООД","Object":"Производствено - складова сграда","Region":"Панчарево","Terrain":"С. КАЗИЧАНЕ","RegulationNeighbourhood":"1","Upi":"V - 1965","Identifier":"35239.6109.1965","Address":""},{"Number":"237/21.09.2018","Hash":"42vtt2_F_Ys=","DocumentTypeName":"Разрешение за строеж","Status":"Влязъл в сила","TakeEffectFilter":"\/Date(1540414800000)\/","TakeEffect":{"DateTime":"\/Date(1540414800000)\/","FilterText":null},"Issuer":"Главен архитект на Столична община","Employer":"Люба Костакева, Светослав Костакев, Даниел Стоянов, Мартин Стоянов, Пенка Костова, Ана Костова-Петрова, Цветана Матеева, Здравка Гиздова-Томова, Георги Гиздов","Object":"МНОГОФАМИЛНА ЖИЛИЩНА СГРАДА С ПОДЗЕМЕН ПАРКИНГ","Region":"Възраждане","Terrain":"\"ЗОНА-Б-4\"","RegulationNeighbourhood":"132","Upi":"I-15","Identifier":"68134.301.129","Address":"гр. София"},{"Number":"178/21.09.2018","Hash":"DhUTGNSdblM=","DocumentTypeName":"Разрешение за строеж","Status":"Влязъл в сила","TakeEffectFilter":"\/Date(1540414800000)\/","TakeEffect":{"DateTime":"\/Date(1540414800000)\/","FilterText":null},"Issuer":"Главен архитект на СО - р-н \"Панчарево\"","Employer":"Евлоги Георгиев","Object":"Жилищна сграда със ЗП=234,65 кв.м, РЗП= 478,30 кв.м и изгребна яма","Region":"Панчарево","Terrain":"с. Лозен","RegulationNeighbourhood":"138","Upi":"XII - 4839","Identifier":"44063.6227.4839","Address":"с. Лозен, ул. Теменуга"},{"Number":"65/21.09.2018","Hash":"5OBEDp5Z_iQ=","DocumentTypeName":"Разрешение за строеж","Status":"Влязъл в сила","TakeEffectFilter":"\/Date(1539550800000)\/","TakeEffect":{"DateTime":"\/Date(1539550800000)\/","FilterText":null},"Issuer":"Главен архитект на СО - р-н \"Връбница\"","Employer":"Любен  Колев, Пенка  Колева","Object":"Преустройство и реконструкция на съществуваща жилищна сграда","Region":"Връбница","Terrain":"МОДЕРНО ПРЕДГРАДИЕ - БУЛ. СЛИВНИЦА","RegulationNeighbourhood":null,"Upi":null,"Identifier":"68134.2823.803","Address":"гр. София, ул. Виткова ливада № 12"},{"Number":"176/21.09.2018","Hash":"J1swHBHB57Q=","DocumentTypeName":"Разрешение за строеж","Status":"Влязъл в сила","TakeEffectFilter":"\/Date(1539723600000)\/","TakeEffect":{"DateTime":"\/Date(1539723600000)\/","FilterText":null},"Issuer":"Главен архитект на СО - р-н \"Панчарево\"","Employer":"Пламен Георгиев, Ванеса Георгиева","Object":"Жилищна сграда със ЗП=75,15 кв.м, РЗП= 125,07кв.м и изгребна яма","Region":"Панчарево","Terrain":"В.З. КОСАНИН ДОЛ","RegulationNeighbourhood":"1","Upi":"XVI - 681","Identifier":"04234.6916.728","Address":"с. Бистрица"},{"Number":"175/21.09.2018","Hash":"kdwF55lszYw=","DocumentTypeName":"Разрешение за строеж","Status":"Влязъл в сила","TakeEffectFilter":"\/Date(1540414800000)\/","TakeEffect":{"DateTime":"\/Date(1540414800000)\/","FilterText":null},"Issuer":"Главен архитект на СО - р-н \"Панчарево\"","Employer":"Мартин Зафиров","Object":"Жилищна сграда с гаражи със ЗП=122,10 кв.м, РЗП= 268,10 кв.м  и изгребна яма","Region":"Панчарево","Terrain":"с. Панчарево","RegulationNeighbourhood":null,"Upi":null,"Identifier":"55419.6707.3200","Address":"с. Панчарево"},{"Number":"100/21.09.2018","Hash":"XP_l_z11mTw=","DocumentTypeName":"Разрешение за строеж","Status":"Влязъл в сила","TakeEffectFilter":"\/Date(1538946000000)\/","TakeEffect":{"DateTime":"\/Date(1538946000000)\/","FilterText":null},"Issuer":"Главен архитект на СО - р-н \"Нови Искър\"","Employer":"Ихаб Ел Аши","Object":"Складове за промишлени стоки и офиси","Region":"Нови Искър","Terrain":"МИРОВЯНЕ, СТОПАНСКИ ДВОР","RegulationNeighbourhood":"46","Upi":"III-657","Identifier":"48393.4990.657","Address":"с. Мировяне"},{"Number":"174/21.09.2018","Hash":"pB3SqESlCsA=","DocumentTypeName":"Разрешение за строеж","Status":"Влязъл в сила","TakeEffectFilter":"\/Date(1539637200000)\/","TakeEffect":{"DateTime":"\/Date(1539637200000)\/","FilterText":null},"Issuer":"Главен архитект на СО - р-н \"Панчарево\"","Employer":"\"ЕКСАЛКО - БЪЛГАРИЯ\" АД","Object":"\"Преустройство на складове в магазини и кафе\" -  Етап 1, и \"Вътрешно преустройство на складове\" Етап 2 в \"Полифункционален център Ексалко България АД\"","Region":"Панчарево","Terrain":"м.\"Голямата локва - Търговски парк 2\"","RegulationNeighbourhood":"37","Upi":"III - 3","Identifier":"68134.6001.3 и 68134.6001.196","Address":"гр. София, ул. Ботевградско шосе № 348"},{"Number":"173/21.09.2018","Hash":"1eWI4QcBY5o=","DocumentTypeName":"Разрешение за строеж","Status":"Влязъл в сила","TakeEffectFilter":"\/Date(1539637200000)\/","TakeEffect":{"DateTime":"\/Date(1539637200000)\/","FilterText":null},"Issuer":"Главен архитект на СО - р-н \"Панчарево\"","Employer":"Ирена Стоянова, Петьо Петков, Любомира Петкова","Object":"Еднофамилна жилищна сграда със ЗП= 200,58 кв.м, РЗП= 318,06 кв.м и изгребна яма","Region":"Панчарево","Terrain":"с. Панчарево","RegulationNeighbourhood":null,"Upi":null,"Identifier":"55419.6707.774","Address":"с. Панчарево"},{"Number":"55/21.09.2018","Hash":"B4471o0IvIc=","DocumentTypeName":"Разрешение за строеж","Status":"Влязъл в сила","TakeEffectFilter":"\/Date(1539118800000)\/","TakeEffect":{"DateTime":"\/Date(1539118800000)\/","FilterText":null},"Issuer":"Главен архитект на СО - р-н \"Младост\"","Employer":"СТОЛИЧНА ОБЩИНА - РАЙОН МЛАДОСТ","Object":"Открита детска площадка - ЕКО КЪТ","Region":"Младост","Terrain":"м. Младост 1","RegulationNeighbourhood":"4","Upi":"I","Identifier":"68134.4082.712","Address":"гр. София, кв. ж.к. \"Младост 1\""},{"Number":"172/21.09.2018","Hash":"rGmTjuQF2ic=","DocumentTypeName":"Разрешение за строеж","Status":"Влязъл в сила","TakeEffectFilter":"\/Date(1540155600000)\/","TakeEffect":{"DateTime":"\/Date(1540155600000)\/","FilterText":null},"Issuer":"Главен архитект на СО - р-н \"Панчарево\"","Employer":"Велин Харбазов","Object":"Еднофамилна жилищна сграда със ЗП=135,40 кв.м, РЗП= 296,90 кв.м, допълващо застрояване - подземен гараж със ЗП= 94,30 кв.м  и изгребна яма ","Region":"Панчарево","Terrain":"с. Бистрица","RegulationNeighbourhood":"5Д","Upi":"XXIII - 2060","Identifier":"04234.6966.3862","Address":"с. Бистрица"},{"Number":"22/21.09.2018","Hash":"N-0eWZOlQT0=","DocumentTypeName":"Разрешение за строеж","Status":"Влязъл в сила","TakeEffectFilter":"\/Date(1539550800000)\/","TakeEffect":{"DateTime":"\/Date(1539550800000)\/","FilterText":null},"Issuer":"Главен архитект на СО - р-н \"Изгрев\"","Employer":"Емилия Савова","Object":"Промяна на предназначението на магазин за промишлени стоки във фризьорски салон","Region":"Изгрев","Terrain":"\"ДИАНАБАД\"","RegulationNeighbourhood":"23","Upi":"IV--1609, 1588","Identifier":"кв. Изток","Address":"гр. София, ул. Апостол Карамитев № 16"},{"Number":"236/21.09.2018","Hash":"pPrir2m_Kkc=","DocumentTypeName":"Разрешение за строеж","Status":"Влязъл в сила","TakeEffectFilter":"\/Date(1539550800000)\/","TakeEffect":{"DateTime":"\/Date(1539550800000)\/","FilterText":null},"Issuer":"Главен архитект на Столична община","Employer":"ДИАНА  ООД","Object":"ПРЕУСТРОЙСТВО НА АПАРТАМЕНТИ НА КОТА +9,30 (ОБЕДИНЯВАНЕ НА АП.№6 И АП.№7)  И НА КОТА +12,45(ОБЕДИНЯВАНЕ НА АП.№8 И АП.№9) В ЖИЛИЩНА СГРАДА","Region":"Изгрев","Terrain":"\"ИЗТОК - ИЗТОК\u0027","RegulationNeighbourhood":"9","Upi":"ІV-53","Identifier":"68134.801.53","Address":""},{"Number":"171/21.09.2018","Hash":"L9b-71Hgq98=","DocumentTypeName":"Разрешение за строеж","Status":"Влязъл в сила","TakeEffectFilter":"\/Date(1539637200000)\/","TakeEffect":{"DateTime":"\/Date(1539637200000)\/","FilterText":null},"Issuer":"Главен архитект на СО - р-н \"Панчарево\"","Employer":"Борислав Антонов","Object":"Жилищни сгради с допълващо застрояване за магазин и гараж: Етап 1 - Еднофамилна жилищна сграда със ЗП=159,64 кв.м, РЗП= 169,53 кв.м и изгребна яма; Етап 2 - Жилищна сграда с допълващо застрояване за магазин и гараж със ЗП=159,05 кв.м, РЗП= 318,10 кв.м. ","Region":"Панчарево","Terrain":"с. Казичене","RegulationNeighbourhood":"48","Upi":"XXI - 1067","Identifier":"35239.6108.1067","Address":"с. Казичене"},{"Number":"99/20.09.2018","Hash":"8RqzZzCDwVk=","DocumentTypeName":"Разрешение за строеж","Status":"Влязъл в сила","TakeEffectFilter":"\/Date(1538946000000)\/","TakeEffect":{"DateTime":"\/Date(1538946000000)\/","FilterText":null},"Issuer":"Главен архитект на СО - р-н \"Нови Искър\"","Employer":"Анастасия Петрова","Object":"Стопански навес","Region":"Нови Искър","Terrain":"ДОБРОСЛАВЦИ","RegulationNeighbourhood":"52","Upi":"XIV-583","Identifier":"21662.4820.1053","Address":"с. Доброславци, ул. \"Здравец\""},{"Number":"170/20.09.2018","Hash":"L5Zl-2XsrIc=","DocumentTypeName":"Разрешение за строеж","Status":"Влязъл в сила","TakeEffectFilter":"\/Date(1539205200000)\/","TakeEffect":{"DateTime":"\/Date(1539205200000)\/","FilterText":null},"Issuer":"Главен архитект на СО - р-н \"Панчарево\"","Employer":"\"ЛАЗАР КОНСУЛТ И ИНВЕСТ\" ЕООД","Object":"Жилищна сграда - къща за гости със заведение за хранене, спортни съоръжения и изгребна яма ; Етап 2 - Жилищна сграда - къща за гости със заведение за хранене със ЗП= 623,76 кв.м, РЗП= 1303,34 кв.м и открит плувен басейн с размери 25,00м / 12,50м , дълбочина 1,35м до 1,65 м, и малък басейн с площ от 20,00 кв.м","Region":"Панчарево","Terrain":" Детски град - Панчарево","RegulationNeighbourhood":"9А","Upi":"I -436,261,262,263,264,265,266,267,277","Identifier":"55419.6702.1030","Address":"с. Панчарево"},{"Number":"235/20.09.2018","Hash":"9FV14n_nbyo=","DocumentTypeName":"Разрешение за строеж","Status":"Влязъл в сила","TakeEffectFilter":"\/Date(1541109600000)\/","TakeEffect":{"DateTime":"\/Date(1541109600000)\/","FilterText":null},"Issuer":"Главен архитект на Столична община","Employer":"\"ТЕХПАРК РЕЗИДЪНС\" ООД","Object":"Мултифункционална сграда с жилища, хотел, търговски обекти, подземен паркинг, трафопост, СВО, СКО и ограда с плътна част  1,2 м. по вътрешни регулационни линии, изцяло разположена в границите на имота","Region":"Младост","Terrain":"НПЗ  ИЗТОК-М. КЪРО","RegulationNeighbourhood":"12","Upi":"VI - \"За жс, администр. и магазини\"","Identifier":"68134.4081.1426","Address":""},{"Number":"169/20.09.2018","Hash":"dotS92aNR7Y=","DocumentTypeName":"Разрешение за строеж","Status":"Влязъл в сила","TakeEffectFilter":"\/Date(1539896400000)\/","TakeEffect":{"DateTime":"\/Date(1539896400000)\/","FilterText":null},"Issuer":"Главен архитект на СО - р-н \"Панчарево\"","Employer":"Соня Рангелова","Object":"Еднофамилна жилищна сграда със ЗП= РЗП= 82,35 кв.м и изгребна яма","Region":"Панчарево","Terrain":"С.  ГЕРМАН","RegulationNeighbourhood":"4","Upi":"IV - 510","Identifier":"14831.6501.510","Address":"с. Герман"},{"Number":"168/20.09.2018","Hash":"ifK6FJ2LeG4=","DocumentTypeName":"Разрешение за строеж","Status":"Влязъл в сила","TakeEffectFilter":"\/Date(1539291600000)\/","TakeEffect":{"DateTime":"\/Date(1539291600000)\/","FilterText":null},"Issuer":"Главен архитект на СО - р-н \"Панчарево\"","Employer":"Емил Янев","Object":"Плътна ограда с височина H= 2,20м и дължина L=90,37м изцяло разположена в УПИ X -2040","Region":"Панчарево","Terrain":"В. З. МАЛИНОВА ДОЛИНА - ГЕРЕНА","RegulationNeighbourhood":"6","Upi":"X - 2040","Identifier":"04234.6906.2040","Address":"с. Бистрица"},{"Number":"167/20.09.2018","Hash":"xziEoyKxs24=","DocumentTypeName":"Разрешение за строеж","Status":"Влязъл в сила","TakeEffectFilter":"\/Date(1539205200000)\/","TakeEffect":{"DateTime":"\/Date(1539205200000)\/","FilterText":null},"Issuer":"Главен архитект на СО - р-н \"Панчарево\"","Employer":"Христо Даскалов","Object":"Еднофамилна жилищна сграда със ЗП= 139,20 кв.м, РЗП=289,90 кв.м и изгребна яма","Region":"Панчарево","Terrain":"В.З КОСАНИН ДОЛ","RegulationNeighbourhood":"40А","Upi":"V -141","Identifier":"04234.6915.3275","Address":"с. Бистрица"},{"Number":"166/20.09.2018","Hash":"QXnl_xSc0t4=","DocumentTypeName":"Разрешение за строеж","Status":"Влязъл в сила","TakeEffectFilter":"\/Date(1539205200000)\/","TakeEffect":{"DateTime":"\/Date(1539205200000)\/","FilterText":null},"Issuer":"Главен архитект на СО - р-н \"Панчарево\"","Employer":"Христо Даскалов","Object":"Плътна ограда с височина H до 2,20м, и дължина L= 84,81м изцяло разположена в УПИ V-141; Подпорни стени с височина до 1,20м и дължина - 2,99м и Подпорни стени с височина до 2,20м и дължина -18,86м","Region":"Панчарево","Terrain":"В.З КОСАНИН ДОЛ","RegulationNeighbourhood":"40А","Upi":"V -141","Identifier":"04234.6915.3275","Address":"с. Бистрица"},{"Number":"61/20.09.2018","Hash":"vnJD0gKmId0=","DocumentTypeName":"Разрешение за строеж","Status":"Влязъл в сила","TakeEffectFilter":"\/Date(1539118800000)\/","TakeEffect":{"DateTime":"\/Date(1539118800000)\/","FilterText":null},"Issuer":"Главен архитект на СО - р-н \"Красно село\"","Employer":"Пламен  Кънев","Object":"Остъкляване на част от покривни тераси към ап. 6.2","Region":"Красно село","Terrain":"\"Бели брези\"","RegulationNeighbourhood":"9","Upi":"IX - 421,422","Identifier":"","Address":"гр. София, ул. \"Дойран\" № 10"},{"Number":"233/19.09.2018","Hash":"zBlybAC6oqU=","DocumentTypeName":"Разрешение за строеж","Status":"Влязъл в сила","TakeEffectFilter":"\/Date(1539291600000)\/","TakeEffect":{"DateTime":"\/Date(1539291600000)\/","FilterText":null},"Issuer":"Главен архитект на Столична община","Employer":"\"ТОПЛОФИКАЦИЯ СОФИЯ\" ЕАД","Object":"Изграждане на инсталация за комбинирано производство на енергия в София с оползотворяване на RDF отпадък","Region":"Сердика","Terrain":"2-РА ИНДУСТРИАЛНА ЗОНА \"ВОЕННА РАМПА\"-ЗАПАД","RegulationNeighbourhood":"22","Upi":"XV 1456, за инсталация за комбинирано производство на енергия с оползотворяване на RDF отпадък","Identifier":"68134.511.1456","Address":""},{"Number":"98/19.09.2018","Hash":"gAuEKs1NEPs=","DocumentTypeName":"Разрешение за строеж","Status":"Влязъл в сила","TakeEffectFilter":"\/Date(1538686800000)\/","TakeEffect":{"DateTime":"\/Date(1538686800000)\/","FilterText":null},"Issuer":"Главен архитект на СО - р-н \"Нови Искър\"","Employer":"Маргарита  Василева, Трифон Василев","Object":"Лятна кухня и лека постройка за инвентар","Region":"Нови Искър","Terrain":"ПОДГУМЕР","RegulationNeighbourhood":"6А","Upi":"VI-414 \"жил. стр.\"","Identifier":"57011.5548.509","Address":"с. Подгумер, ул. Китка № 8"},{"Number":"232/19.09.2018","Hash":"Ji3FCl7EmGY=","DocumentTypeName":"Разрешение за строеж","Status":"Влязъл в сила","TakeEffectFilter":"\/Date(1539291600000)\/","TakeEffect":{"DateTime":"\/Date(1539291600000)\/","FilterText":null},"Issuer":"Главен архитект на Столична община","Employer":"\"СОФИЯ САУТ РИНГ МОЛ\" ЕАД","Object":"Преустройство на помещение 0.17а в магазин за хранителни стоки \"Берьозка\", на ниво кота -7.22м. на Търговски комплекс \"София Саут Ринг Мол","Region":"Витоша","Terrain":"В.З. МАЛИНОВА ДОЛИНА - БУНКЕРА - 3","RegulationNeighbourhood":"1","Upi":"II - 908, 950, 927","Identifier":"","Address":""},{"Number":"231/19.09.2018","Hash":"DX6Baal36E0=","DocumentTypeName":"Разрешение за строеж","Status":"Влязъл в сила","TakeEffectFilter":"\/Date(1539723600000)\/","TakeEffect":{"DateTime":"\/Date(1539723600000)\/","FilterText":null},"Issuer":"Главен архитект на Столична община","Employer":"\"ВОЛАН 98\" ООД, Васил Русев, Анна Русева, Констанс Русева, Милкана Русева, Веселка Русева, Йордан Русев, Васил Русев, Милка Русева","Object":"Високоетажна жилищна сграда с подземен гараж","Region":"Възраждане","Terrain":"ЗАПАДНО НАПРАВЛЕЛИЕ -МЕТРОСТАНЦИЯ","RegulationNeighbourhood":"181","Upi":"II - 12","Identifier":"68134.301.402","Address":"гр. София, ул. Пиротска № 73"},{"Number":"230/18.09.2018","Hash":"ig19HxJ4H90=","DocumentTypeName":"Разрешение за строеж","Status":"Влязъл в сила","TakeEffectFilter":"\/Date(1540936800000)\/","TakeEffect":{"DateTime":"\/Date(1540936800000)\/","FilterText":null},"Issuer":"Главен архитект на Столична община","Employer":"\"СОФАРМА\" АД","Object":"Подмяна на инсталации в съществуващ склад за съхранение на готови лекарствени средства \"Терминал 1","Region":"Надежда","Terrain":"НПЗ  ВОЕННА РАМПА - ЗАПАД","RegulationNeighbourhood":"10","Upi":"I-735 - \"За производство, складове и офиси\"","Identifier":"68134.1380.2109.3; 68134.1380.2109.4; 68134.1380.2109.12;","Address":"гр. София, ул. \"Рожен\" № 16"},{"Number":"229/18.09.2018","Hash":"X89U_g-6w78=","DocumentTypeName":"Разрешение за строеж","Status":"Влязъл в сила","TakeEffectFilter":"\/Date(1539550800000)\/","TakeEffect":{"DateTime":"\/Date(1539550800000)\/","FilterText":null},"Issuer":"Главен архитект на Столична община","Employer":"ДЕЙЗИ ТЕХНОЛОДЖИ ЕООД, \"ПЛАСТО\" ЕООД","Object":"Високоетажна офисна сграда с подземен гараж на три нива, абонатна станция, кафене, СВО и СКО","Region":"Изгрев","Terrain":"НПЯ - ЧЕРВЕНА ЗВЕЗДА","RegulationNeighbourhood":"2ж","Upi":"III за офиси, магазини, ателиета, жилища и гаражи","Identifier":"68134.803.3995","Address":""},{"Number":"228/18.09.2018","Hash":"d9Z7pjw2oec=","DocumentTypeName":"Разрешение за строеж","Status":"Влязъл в сила","TakeEffectFilter":"\/Date(1539550800000)\/","TakeEffect":{"DateTime":"\/Date(1539550800000)\/","FilterText":null},"Issuer":"Главен архитект на Столична община","Employer":"ДЕЙЗИ ТЕХНОЛОДЖИ ЕООД, \"ПЛАСТО\" ЕООД","Object":"Високоетажна жилищна сграда с подземен гараж на три нива, ателиета, офис, магазин за промишлени стоки, заведение за обществено хранене, помещение за абонатна станция, СВО и СКО","Region":"Изгрев","Terrain":"НПЯ - ЧЕРВЕНА ЗВЕЗДА","RegulationNeighbourhood":"2ж","Upi":"III за офиси, магазини, ателиета, жилища и гаражи","Identifier":"68134.803.3995","Address":""},{"Number":"227/18.09.2018","Hash":"vstvBdXUN1g=","DocumentTypeName":"Разрешение за строеж","Status":"Влязъл в сила","TakeEffectFilter":"\/Date(1539291600000)\/","TakeEffect":{"DateTime":"\/Date(1539291600000)\/","FilterText":null},"Issuer":"Главен архитект на Столична община","Employer":"\"СОФИЯ САУТ РИНГ МОЛ\" ЕАД","Object":"Преустройство на Магазин №0.15 / помещение 0.15 / на кота -7,22 м. в Студио за красота, находящ се в Търговски комплекс \"София Саут Ринг Мол","Region":"Витоша","Terrain":"В.З. МАЛИНОВА ДОЛИНА - БУНКЕРА - ЕТАП III","RegulationNeighbourhood":"1","Upi":"II-908, 950, 927","Identifier":"","Address":"гр. София"},{"Number":"226/18.09.2018","Hash":"Ugt0ILtdu74=","DocumentTypeName":"Разрешение за строеж","Status":"Влязъл в сила","TakeEffectFilter":"\/Date(1539723600000)\/","TakeEffect":{"DateTime":"\/Date(1539723600000)\/","FilterText":null},"Issuer":"Главен архитект на Столична община","Employer":"Иван  Иванов","Object":"Многофункционална сграда с офиси, магазини, подземен паркинг и помещение за трафопост","Region":"Лозенец","Terrain":"НПЗ ХЛАДИЛНИКА ВИТОША - ЧАСТ ЮГ","RegulationNeighbourhood":"5","Upi":"IX - \"За офиси и общ. обслужване\"","Identifier":"68134.903.1834","Address":""},{"Number":"66/18.09.2018","Hash":"Msu87wtzR_I=","DocumentTypeName":"Разрешение за строеж","Status":"Влязъл в сила","TakeEffectFilter":"\/Date(1538600400000)\/","TakeEffect":{"DateTime":"\/Date(1538600400000)\/","FilterText":null},"Issuer":"Главен архитект на СО - р-н \"Овча купел\"","Employer":"Ивайло Стоев","Object":"ДЪРВЕНА ПРИСТРОЙКА -СКЛАД ЗА СТЪКЛЕН АМБАЛАЖ КЪМ СЪЩЕСТВУВАЩА РАБОТИЛНИЦА ЗА СПЕЦИАЛИЗИРАНИ СТУДЕНИ ЧАЙОВЕ","Region":"Овча купел","Terrain":"м. \"кв. Горна баня\"","RegulationNeighbourhood":"100а","Upi":"І -266 за общ. обсл.","Identifier":" 68134.4326.145","Address":"гр. София, ул. \"Николай  Хрелков\" № 70"},{"Number":"97/18.09.2018","Hash":"qrrpKU-NvvI=","DocumentTypeName":"Разрешение за строеж","Status":"Влязъл в сила","TakeEffectFilter":"\/Date(1538946000000)\/","TakeEffect":{"DateTime":"\/Date(1538946000000)\/","FilterText":null},"Issuer":"Главен архитект на СО - р-н \"Нови Искър\"","Employer":"Емил Джанов","Object":"Автоработилница с офис","Region":"Нови Искър","Terrain":"МИРОВЯНЕ","RegulationNeighbourhood":"7","Upi":"VII-584","Identifier":"48393.4989.584","Address":"с. Мировяне, ул. \"Леденика\"  № 2"},{"Number":"225/14.09.2018","Hash":"-uMrWpCzfow=","DocumentTypeName":"Разрешение за строеж","Status":"Влязъл в сила","TakeEffectFilter":"\/Date(1539118800000)\/","TakeEffect":{"DateTime":"\/Date(1539118800000)\/","FilterText":null},"Issuer":"Главен архитект на Столична община","Employer":"ТИ КЕЙ ЕЙЧ БЪЛГАРИЯ ЕООД","Object":"Хотел с подземен гараж и помещение за трафопост","Region":"Красно село","Terrain":"ХИПОДРУМА","RegulationNeighbourhood":"8","Upi":"VII-1285-\"за общежитие, хотел и ОО\"","Identifier":"68134.204.1285","Address":"гр. София"},{"Number":"224/14.09.2018","Hash":"sE74njLOgpU=","DocumentTypeName":"Разрешение за строеж","Status":"Влязъл в сила","TakeEffectFilter":"\/Date(1538946000000)\/","TakeEffect":{"DateTime":"\/Date(1538946000000)\/","FilterText":null},"Issuer":"Главен архитект на Столична община","Employer":"\"ЛИДЛ България ЕООД енд КО\" КД","Object":"Магазин за хранителни и битови стоки тип \"ЛИДЛ\" с помещение за подготовка на хляб и хлебни изделия","Region":"Връбница","Terrain":"СТОПАНСКИ ДВОР ВРЪБНИЦА","RegulationNeighbourhood":"1","Upi":"I- 47","Identifier":"68134.2815.47","Address":"гр. София"},{"Number":"9/14.09.2018","Hash":"gKiljOgs8YI=","DocumentTypeName":"Разрешение за строеж","Status":"Влязъл в сила","TakeEffectFilter":"\/Date(1538686800000)\/","TakeEffect":{"DateTime":"\/Date(1538686800000)\/","FilterText":null},"Issuer":"Главен архитект на СО - р-н \"Красна поляна\"","Employer":"\"СКАМЕТРАНС\" ЕООД","Object":"Складова база с офиси и подземни гаражи","Region":"Красна поляна","Terrain":"ТЕРЕН ОТРЕДЕН ЗА ТРУДОВИ ВОЙСКИ В С. СУХОДОЛ","RegulationNeighbourhood":"1","Upi":"XX-223-ЗА ОФИСИ, АВТОСЕРВИЗ, ГТП","Identifier":"68134.1113.223","Address":"гр. София, ул. УЛ. СУХОДОЛСКА"},{"Number":"65/14.09.2018","Hash":"uWeM3VJxrPs=","DocumentTypeName":"Разрешение за строеж","Status":"Влязъл в сила","TakeEffectFilter":"\/Date(1538427600000)\/","TakeEffect":{"DateTime":"\/Date(1538427600000)\/","FilterText":null},"Issuer":"Главен архитект на СО - р-н \"Овча купел\"","Employer":"\"СТАТЕХ 2000\" ООД","Object":"ЕДНОФАМИЛНА ЖИЛИЩНА СГРАДА","Region":"Овча купел","Terrain":"м. в.з.Горна баня","RegulationNeighbourhood":"49","Upi":"ІІ -753","Identifier":"68134.4329.753","Address":"гр. София, ул. \"Черешова градина\" № 14"},{"Number":"28/14.09.2018","Hash":"qA36nWI7bBk=","DocumentTypeName":"Разрешение за строеж","Status":"Влязъл в сила","TakeEffectFilter":"\/Date(1538341200000)\/","TakeEffect":{"DateTime":"\/Date(1538341200000)\/","FilterText":null},"Issuer":"Главен архитект на СО - р-н \"Средец\"","Employer":"\"МЛАДЕЖКА \"ЯЛТА\"\"","Object":"Монтаж на съоражения - два броя ескалатори в търговски обект","Region":"Средец","Terrain":"м. „Център - Зона „А“ - юг“","RegulationNeighbourhood":"473","Upi":"VI-48","Identifier":"68134.100.48.1.30","Address":"гр. София, ул. \"Съборна\" № 3"},{"Number":"66/13.09.2018","Hash":"zTaJRh0zXBM=","DocumentTypeName":"Разрешение за строеж","Status":"Влязъл в сила","TakeEffectFilter":"\/Date(1538600400000)\/","TakeEffect":{"DateTime":"\/Date(1538600400000)\/","FilterText":null},"Issuer":"Главен архитект на СО - р-н \"Люлин\"","Employer":"СТОЛИЧНА ОБЩИНА","Object":"Открита детска площадка за деца от 3 до 12 г.","Region":"Люлин","Terrain":"Ж.К. \"ЛЮЛИН - 3 М.Р.\"","RegulationNeighbourhood":"37","Upi":"I","Identifier":"69134.4361.67","Address":"гр. София"},{"Number":"51/13.09.2018","Hash":"uyj3UNiXOe4=","DocumentTypeName":"Разрешение за строеж","Status":"Влязъл в сила","TakeEffectFilter":"\/Date(1540242000000)\/","TakeEffect":{"DateTime":"\/Date(1540242000000)\/","FilterText":null},"Issuer":"Главен архитект на СО - р-н \"Слатина\"","Employer":"Асения Димитрова","Object":"ЖИЛИЩНА СГРАДА И ДОПЪЛВАЩО ЗАСТРОЯВАНЕ - ТЪРГОВСКИ ОБЕКТ","Region":"Слатина","Terrain":"\"Христо Ботев\"","RegulationNeighbourhood":"51","Upi":"I-1190","Identifier":"68134.707.4999","Address":"гр. София, ул. 518 № 9а, кв. Христо Ботев"},{"Number":"165/12.09.2018","Hash":"nPGD1JMBYew=","DocumentTypeName":"Разрешение за строеж","Status":"Влязъл в сила","TakeEffectFilter":"\/Date(1539550800000)\/","TakeEffect":{"DateTime":"\/Date(1539550800000)\/","FilterText":null},"Issuer":"Главен архитект на СО - р-н \"Панчарево\"","Employer":"Борис  Петков","Object":"Жилищна сграда със ЗП=117,00 кв.м, РЗП=348,53 кв.м и изгребна яма","Region":"Панчарево","Terrain":"ТЕРАСИТЕ - с. Герман  ","RegulationNeighbourhood":null,"Upi":null,"Identifier":"14831.6506.427","Address":""},{"Number":"164/12.09.2018","Hash":"V2hly797bHY=","DocumentTypeName":"Разрешение за строеж","Status":"Влязъл в сила","TakeEffectFilter":"\/Date(1539205200000)\/","TakeEffect":{"DateTime":"\/Date(1539205200000)\/","FilterText":null},"Issuer":"Главен архитект на СО - р-н \"Панчарево\"","Employer":"Ивайла Николова, Венцислав Николов","Object":"Основен ремонт на покрив с надзид на жилищна сграда с идентификатор 35239.6107.734.1","Region":"Панчарево","Terrain":"с. Казичене","RegulationNeighbourhood":"60","Upi":"XVII - 734","Identifier":"35239.6107.734","Address":"с. Казичене, ул. Христо Ботев № 14"},{"Number":"50/12.09.2018","Hash":"wDru0umKcI0=","DocumentTypeName":"Разрешение за строеж","Status":"Влязъл в сила","TakeEffectFilter":"\/Date(1538427600000)\/","TakeEffect":{"DateTime":"\/Date(1538427600000)\/","FilterText":null},"Issuer":"Главен архитект на СО - р-н \"Слатина\"","Employer":"\"ТЕЛЕНОР БЪЛГАРИЯ\" ЕАД  , Етажна собственост на ул. 205","Object":"ОПТИЧНА СВЪРЗАНОСТ НА БАЗОВА СТАНЦИЯ ID №1443","Region":"Слатина","Terrain":"\"Гео Милев-Подуене-Редута\"","RegulationNeighbourhood":"26","Upi":"II","Identifier":"68134.702.911.1","Address":"гр. София, ул. \"Христо Максимов\" № 1, бл. 205"},{"Number":"54/12.09.2018","Hash":"6KlKwA5lQPc=","DocumentTypeName":"Разрешение за строеж","Status":"Влязъл в сила","TakeEffectFilter":"\/Date(1538341200000)\/","TakeEffect":{"DateTime":"\/Date(1538341200000)\/","FilterText":null},"Issuer":"Главен архитект на СО - р-н \"Младост\"","Employer":"Ивайло  Тодоров, Вероника  Чорбаджиева","Object":"Обединяване и преустройство на Апартамент № Е-152 и Апартамент № Е-153 в Апартамент № Е-152","Region":"Младост","Terrain":"\"МЛАДОСТ 3\"","RegulationNeighbourhood":"2а","Upi":"II - 786","Identifier":"68134.4083.6143.4","Address":"гр. София, кв. ж.к. \"Младост 3\", бл. 389, вх. 6, ет. 3"},{"Number":"49/12.09.2018","Hash":"n_ZAeao7Z_I=","DocumentTypeName":"Разрешение за строеж","Status":"Влязъл в сила","TakeEffectFilter":"\/Date(1538427600000)\/","TakeEffect":{"DateTime":"\/Date(1538427600000)\/","FilterText":null},"Issuer":"Главен архитект на СО - р-н \"Слатина\"","Employer":"\"ТЕЛЕНОР БЪЛГАРИЯ\" ЕАД  , Етажна собственост на ул. 3","Object":"ОПТИЧНА СВЪРЗАНОСТ НА БАЗОВА СТАНЦИЯ ID №1615","Region":"Слатина","Terrain":"\"Гео Милев-Подуене-Редута\"","RegulationNeighbourhood":"179","Upi":"I за ожс","Identifier":"68134.702.1112.6","Address":"гр. София, ул. \"Плачковски манастир\" № 18, бл. 3"},{"Number":"221/12.09.2018","Hash":"Xfe-XC2BnfI=","DocumentTypeName":"Разрешение за строеж","Status":"Влязъл в сила","TakeEffectFilter":"\/Date(1539118800000)\/","TakeEffect":{"DateTime":"\/Date(1539118800000)\/","FilterText":null},"Issuer":"Главен архитект на Столична община","Employer":"Иванка Георгиева-Чарамелла, Емилия Илиева, Богомил   Николов","Object":"ЖИЛИЩНА СГРАДА С ПОДЗЕМЕН ГАРАЖ","Region":"Надежда","Terrain":"Ж.К. НАДЕЖДА 3","RegulationNeighbourhood":"15","Upi":"ІІ-2244","Identifier":"68134.1385.2244","Address":"гр. София"},{"Number":"96/12.09.2018","Hash":"XiJRmF2Ex6Q=","DocumentTypeName":"Разрешение за строеж","Status":"Влязъл в сила","TakeEffectFilter":"\/Date(1538427600000)\/","TakeEffect":{"DateTime":"\/Date(1538427600000)\/","FilterText":null},"Issuer":"Главен архитект на СО - р-н \"Нови Искър\"","Employer":"КАМЕЛИЯ ПЕТКОВА","Object":"ЕДНОФАМИЛНА ЕДНОЕТАЖНА ЖИЛИЩНА СГРАДА","Region":"Нови Искър","Terrain":"град Нови Искър - кв. Ал. Войков (Кумарица и Славовци) без квартали 176;177;184.185;187;188;199 и площта за озеленяване от кв.198","RegulationNeighbourhood":"229","Upi":"ХХVІІ - 245","Identifier":"00357.5361.245","Address":"гр. Нови Искър, ул. Стадион"},{"Number":"60/12.09.2018","Hash":"gVRGHhPMi6g=","DocumentTypeName":"Разрешение за строеж","Status":"Влязъл в сила","TakeEffectFilter":"\/Date(1538427600000)\/","TakeEffect":{"DateTime":"\/Date(1538427600000)\/","FilterText":null},"Issuer":"Главен архитект на СО - р-н \"Красно село\"","Employer":"\"ГАБРОВСКИ\" ООД","Object":"Преустройство и разделяне на магазин за осветителни тела със складови площи на два магазина","Region":"Красно село","Terrain":"ж.к. \"Красно село - плавателен канал - север\"","RegulationNeighbourhood":"293а","Upi":"І-за ОЖС, ОО, траф. и паркинг","Identifier":"68134.207.215","Address":"гр. София, ул. \"Пчела\" № 32"},{"Number":"100/10.09.2018","Hash":"KSdinB63T2I=","DocumentTypeName":"Разрешение за строеж","Status":"Влязъл в сила","TakeEffectFilter":"\/Date(1537822800000)\/","TakeEffect":{"DateTime":"\/Date(1537822800000)\/","FilterText":null},"Issuer":"Главен архитект на СО - р-н \"Лозенец\"","Employer":"Николай  Николов, Иван Димитров, Росица Димитрова","Object":"МНОГОФАМИЛНА ЖИЛИЩНА СГРАДА С ГАРАЖИ","Region":"Лозенец","Terrain":"Кръстова вада","RegulationNeighbourhood":"37","Upi":"VI-607, 608","Identifier":"68134.904.608","Address":"гр. София, ул. Борис Руменов № 42"},{"Number":"220/10.09.2018","Hash":"kwEQOl_6unY=","DocumentTypeName":"Разрешение за строеж","Status":"Влязъл в сила","TakeEffectFilter":"\/Date(1538514000000)\/","TakeEffect":{"DateTime":"\/Date(1538514000000)\/","FilterText":null},"Issuer":"Главен архитект на Столична община","Employer":"\"БУЛФЕЛД\" ЕООД","Object":"МНОГОФУНКЦИОНАЛЕН ТЪРГОВСКИ И СПОРТНО-РАЗВЛЕКАТЕЛЕН КОМПЛЕКС - \"ПАРАДАЙЗ ЦЕНТЪР \" - ВЪТРЕШНО ПРЕУСТРОЙСТВО И ПРОМЯНА НА ПРЕДНАЗНАЧЕНИЕТО НА ЧАСТИ ОТ ЕТАЖ -1 НА КОТА - 6,40M. :\r\nЕТАП І МЕЖДУ ОСИ Т23 - Т5 И ОСИ  И ОСИ С9 - FT;\r\n ЕТАП ІІ МЕЖДУ ОСИ Т 4 - Т12 И Е1 - Е9;\r\n ЕТАП ІІІ МЕЖДУ ОСИ С9/С7 - С12 И ОСИ S11-SS19Q;\r\n ЕТАП ІV МЕЖДУ ОСИ Е6 - Е7 И ОСИ S12 - Т5;\r\nЕТАП V МЕЖДУ ОСИ С11 - S15 И ОСИ FS - S24.","Region":"Триадица","Terrain":"Драгалевска спирка","RegulationNeighbourhood":"9","Upi":"I","Identifier":"","Address":"гр. София"},{"Number":"59/07.09.2018","Hash":"qkKyfBGWz4k=","DocumentTypeName":"Разрешение за строеж","Status":"Влязъл в сила","TakeEffectFilter":"\/Date(1537909200000)\/","TakeEffect":{"DateTime":"\/Date(1537909200000)\/","FilterText":null},"Issuer":"Главен архитект на СО - р-н \"Красно село\"","Employer":"\"БИГ ИНВЕСТ 2009\" АД","Object":"Преустройство, разделяне  и промяна предназначението на офис в четири броя ателиета и два магазина","Region":"Красно село","Terrain":"ж.к. \"Красно село - плавателен канал - север\"","RegulationNeighbourhood":"312а","Upi":"ІІІ-60","Identifier":"68134.207.60.1.61","Address":"гр. София, ул. \"Хубча\" № 8"},{"Number":"21/05.09.2018","Hash":"c3V1nGpQJVA=","DocumentTypeName":"Разрешение за строеж","Status":"Влязъл в сила","TakeEffectFilter":"\/Date(1537822800000)\/","TakeEffect":{"DateTime":"\/Date(1537822800000)\/","FilterText":null},"Issuer":"Главен архитект на СО - р-н \"Изгрев\"","Employer":"АГРО ТАУН ЕООД","Object":"Преустройство и промяна на предназначението на съществуващ магазин №23-24 в студио за персонални и групови тренировки","Region":"Изгрев","Terrain":"ДИАНАБАД","RegulationNeighbourhood":"21 б","Upi":"IV-1241","Identifier":"68134.803.1241.1.119","Address":"гр. София"},{"Number":"219/05.09.2018","Hash":"B3gH0LZHDiY=","DocumentTypeName":"Разрешение за строеж","Status":"Влязъл в сила","TakeEffectFilter":"\/Date(1543269600000)\/","TakeEffect":{"DateTime":"\/Date(1543269600000)\/","FilterText":null},"Issuer":"Главен архитект на Столична община","Employer":"Димитрина Петрова, Венцислав Петров","Object":"ПРЕУСТРОЙСТВО НА АПАРТАМЕНТ №33, находящ се в жилищна сграда секция \"В\", бл. №458","Region":"Младост","Terrain":"\"Ж.К. МЛАДОСТ 4\"","RegulationNeighbourhood":"12A","Upi":"II","Identifier":"68134.4089.336","Address":"гр. София, кв. \"Младост 4\", бл. 458, вх. 5, ет. 10, ап. 33"},{"Number":"64/05.09.2018","Hash":"Jjy1MymTzbM=","DocumentTypeName":"Разрешение за строеж","Status":"Влязъл в сила","TakeEffectFilter":"\/Date(1537563600000)\/","TakeEffect":{"DateTime":"\/Date(1537563600000)\/","FilterText":null},"Issuer":"Главен архитект на СО - р-н \"Овча купел\"","Employer":"Илко Жеков","Object":"НОВА ЖИЛИЩНА СГРАДА","Region":"Овча купел","Terrain":"м. в.з.Горна баня","RegulationNeighbourhood":"56","Upi":"XII-4","Identifier":"68134.4329.4","Address":"гр. София, ул. Обзор  № 78"},{"Number":"217/05.09.2018","Hash":"wuxy9h7_4Po=","DocumentTypeName":"Разрешение за строеж","Status":"Влязъл в сила","TakeEffectFilter":"\/Date(1537390800000)\/","TakeEffect":{"DateTime":"\/Date(1537390800000)\/","FilterText":null},"Issuer":"Главен архитект на Столична община","Employer":"СТОЛИЧНА ОБЩИНА, \"МЕТРОПОЛИТЕН\" ЕАД, СТОЛИЧЕН АВТОТРАНСПОРТ ЕАД","Object":"РАЗШИРЕНИЕ НА МЕТРО СОФИЯ,ТРЕТА МЕТРОЛИНИЯ : БУЛ.БОТЕВГРАДСКО ШОСЕ - Ж.К.ОВЧА КУПЕЛ -,ПЪРВИ ЕТАП ОТ КМ 4+320 ДО КМ 11+966,34 - МЕТРОДЕПО ЗЕМЛЯНЕ : ГАРАЖНО  И РЕМОНТНО ХАЛЕ  ОТ ОС 1 ДО ОС 13 - ІІ ЕТАП, КОТЕЛНО , КТП, КОЛОВОЗНО РАЗВИТИЕ  С КОНТАКТНА МРЕЖА, МИВКА ЗА АВТОВЛАКОВЕ, ПЛОЩАДКОВИ ИНЖЕНЕРНИ МРЕЖИ, РЕКОНСТРУКЦИЯ ВиК МРЕЖИ","Region":"Красно село","Terrain":null,"RegulationNeighbourhood":"","Upi":"","Identifier":"","Address":"гр. София"},{"Number":"216/05.09.2018","Hash":"Yw4Ked1-C_g=","DocumentTypeName":"Разрешение за строеж","Status":"Влязъл в сила","TakeEffectFilter":"\/Date(1540764000000)\/","TakeEffect":{"DateTime":"\/Date(1540764000000)\/","FilterText":null},"Issuer":"Главен архитект на Столична община","Employer":"СТОЛИЧНА ОБЩИНА","Object":"РЕКОНСТРУКЦИЯ, ПРИСТРОЯВАНЕ,ЧАСТИЧНО НАДСТРОЯВАНЕ И ПРЕУСТРОЙСТВО НА БИВША ТОПЛОЦЕНТРАЛА НА НДК  В ЦЕНТЪР ЗА ИЗКУСТВА И КУЛТУРА","Region":"Триадица","Terrain":"\"ЮЖЕН ПАРК - II ЧАСТ\"","RegulationNeighbourhood":"1","Upi":"IX-за спорт и атракции","Identifier":"68134.1004.185","Address":"гр. София"},{"Number":"37/05.09.2018","Hash":"mDmSoe4y2pw=","DocumentTypeName":"Разрешение за строеж","Status":"Влязъл в сила","TakeEffectFilter":"\/Date(1536613200000)\/","TakeEffect":{"DateTime":"\/Date(1536613200000)\/","FilterText":null},"Issuer":"Главен архитект на СО - р-н \"Подуяне\"","Employer":"Станимир Тотев","Object":"НИСКОЕТАЖНА ОФИС СГРАДА  С ГАРАЖ И РАБОТИЛНИЦА С КОТА КОРНИЗ ДО  +10,00м И ИЗГРЕБНА ЯМА","Region":"Подуяне","Terrain":"ОСЗ \"СГУРООТВАЛА\"","RegulationNeighbourhood":"2","Upi":"VII-1560-\" за производство, склад и офис\"","Identifier":"68134.603.1428","Address":""},{"Number":"99/05.09.2018","Hash":"j3o5s_Wc-HI=","DocumentTypeName":"Разрешение за строеж","Status":"Влязъл в сила","TakeEffectFilter":"\/Date(1537477200000)\/","TakeEffect":{"DateTime":"\/Date(1537477200000)\/","FilterText":null},"Issuer":"Главен архитект на СО - р-н \"Лозенец\"","Employer":"Трифон  Филипов, Десислава Филипова","Object":"ВЪТРЕШНО ПРЕУСТРОЙСТВО НА АПАРТАМЕНТ №18 В ЖИЛИЩНА СГРАДА","Region":"Лозенец","Terrain":"\"ЛОЗЕНЕЦ - I ЧАСТ\"","RegulationNeighbourhood":"242в","Upi":"IV","Identifier":"68134.900.865","Address":"гр. София, ул. \"Горски пътник\" № 1-7"},{"Number":"63/05.09.2018","Hash":"oqemHM7OaLU=","DocumentTypeName":"Разрешение за строеж","Status":"Влязъл в сила","TakeEffectFilter":"\/Date(1537390800000)\/","TakeEffect":{"DateTime":"\/Date(1537390800000)\/","FilterText":null},"Issuer":"Главен архитект на СО - р-н \"Овча купел\"","Employer":"Димитър Василев","Object":"ВИЛНА СГРАДА","Region":"Овча купел","Terrain":"в.з. Мало Бучино","RegulationNeighbourhood":"10","Upi":"ІІІ -893","Identifier":"46721.3852.893","Address":"с. Мало Бучино, ул. \"Рила\""},{"Number":"62/05.09.2018","Hash":"gujCiim_3EI=","DocumentTypeName":"Разрешение за строеж","Status":"Влязъл в сила","TakeEffectFilter":"\/Date(1537390800000)\/","TakeEffect":{"DateTime":"\/Date(1537390800000)\/","FilterText":null},"Issuer":"Главен архитект на СО - р-н \"Овча купел\"","Employer":"Петър Христов","Object":"ПРОМЯНА НА ПРЕДНАЗНАЧЕНИЕТО НА АТЕЛИЕ № 4 В АПАРТАМЕНТ № 45","Region":"Овча купел","Terrain":"м. \"ж.к. Овча купел 2\"","RegulationNeighbourhood":"14","Upi":"І -332","Identifier":"68134.4333.1401.4 /68134.4333.1401.4.45","Address":"гр. София, кв. \" Овча купел 2\", бл. 2, вх. \"А\", ет. 11, ап. 4"},{"Number":"214/05.09.2018","Hash":"2-5YJ91hEXA=","DocumentTypeName":"Разрешение за строеж","Status":"Влязъл в сила","TakeEffectFilter":"\/Date(1538514000000)\/","TakeEffect":{"DateTime":"\/Date(1538514000000)\/","FilterText":null},"Issuer":"Главен архитект на Столична община","Employer":"УМБАЛСМ \"Н. И. Пирогов\" ЕАД","Object":"Клиника по изгаряния и пластична хирургия към УМБАЛСМ \"Н. И. Пирогов\" ЕАД:\r\n- Етап I - Мерки за енергийна ефективност за сградата на клиниките по изгаряния и пластична хирургия към УМБАЛСМ \"Н. И. Пирогов\" ЕАД;\r\n- Етап II - Преустройство на Операционен блок - кота +12,60;\r\n- Етап III - Преустройство на Детско отделение - кота +9,45;\r\n- Етап IV - Ремонт и реконструкция на отделение по анестезиология и интензивно лечение - кота +6,35;\r\n- Етап V - Преустройство и смяна на предназначение от Административен етаж във Физиотерапия и ЛФК - кота +3,35.","Region":"Красно село","Terrain":"\"БУКАТА\"","RegulationNeighbourhood":"313","Upi":"I - \"за институт Н.И.Пирогов\"","Identifier":"68134.203.281","Address":"гр. София, ул. \"Тотлебен\" № 21"},{"Number":"213/04.09.2018","Hash":"gt4BpKLeRIk=","DocumentTypeName":"Разрешение за строеж","Status":"Влязъл в сила","TakeEffectFilter":"\/Date(1538514000000)\/","TakeEffect":{"DateTime":"\/Date(1538514000000)\/","FilterText":null},"Issuer":"Главен архитект на Столична община","Employer":"\" Р.В.Х.Груп\" ООД, \"КМН 2017\"ООД","Object":"ЖИЛИЩНА СГРАДА С АТЕЛИЕТА,СТУДИА,ЗАВЕДЕНИЕ ЗА ОБЩЕСТВЕНО ХРАНЕНЕ-ФАСТ ФУУД, ПГ и БАСЕЙН","Region":"Красно село","Terrain":"ЛАГЕРА","RegulationNeighbourhood":"53","Upi":"VII-144-за ЖС,ОО,ПГ и басейн","Identifier":"68134.201.144","Address":""},{"Number":"95/04.09.2018","Hash":"Ko9gVBxkuDA=","DocumentTypeName":"Разрешение за строеж","Status":"Влязъл в сила","TakeEffectFilter":"\/Date(1537304400000)\/","TakeEffect":{"DateTime":"\/Date(1537304400000)\/","FilterText":null},"Issuer":"Главен архитект на СО - р-н \"Нови Искър\"","Employer":"Тихомир Симеонов","Object":"\"Жилищна сграда с гараж\"","Region":"Нови Искър","Terrain":"с. Подгумер","RegulationNeighbourhood":null,"Upi":null,"Identifier":"57011.5986.10","Address":"с. Подгумер"},{"Number":"94/04.09.2018","Hash":"DmqrQVMwp5E=","DocumentTypeName":"Разрешение за строеж","Status":"Влязъл в сила","TakeEffectFilter":"\/Date(1539637200000)\/","TakeEffect":{"DateTime":"\/Date(1539637200000)\/","FilterText":null},"Issuer":"Главен архитект на СО - р-н \"Нови Искър\"","Employer":"СТЕФАН МИЛЕНКОВ","Object":"ВТОРОСТЕПЕННА ПОСТРОЙКА за СЪХРАНЯВАНЕ на ПОМОЩНИ МАТЕРИАЛИ, ИНСТРУМЕНТИ и ИНВЕНТАР","Region":"Нови Искър","Terrain":"ГР. НОВИ ИСКЪР, КВ. КУРИЛО","RegulationNeighbourhood":"93","Upi":"ІІ - 73","Identifier":"00357.5357.73","Address":"гр. Нови Искър, ул. Розова долина\" №  1"},{"Number":"98/04.09.2018","Hash":"xZxD8k9odhE=","DocumentTypeName":"Разрешение за строеж","Status":"Влязъл в сила","TakeEffectFilter":"\/Date(1537477200000)\/","TakeEffect":{"DateTime":"\/Date(1537477200000)\/","FilterText":null},"Issuer":"Главен архитект на СО - р-н \"Лозенец\"","Employer":"Александра  Айтова","Object":"РЕМОНТ, РЕКОНСТРУКЦИЯ И НАДСТРОЯВАНЕ НА ЖИЛИЩНА СГРАДА С К.К. до 10 м","Region":"Лозенец","Terrain":"\"ЛОЗЕНЕЦ - III ЧАСТ\"","RegulationNeighbourhood":"127","Upi":"II-431","Identifier":"кв. Долни Лозенец - 2-ри етап, 431","Address":"гр. София, ул. \"Миджур\" № 7"},{"Number":"61/04.09.2018","Hash":"q0b7TlfeChQ=","DocumentTypeName":"Разрешение за строеж","Status":"Влязъл в сила","TakeEffectFilter":"\/Date(1537390800000)\/","TakeEffect":{"DateTime":"\/Date(1537390800000)\/","FilterText":null},"Issuer":"Главен архитект на СО - р-н \"Овча купел\"","Employer":"\"СРЕДЕЦ СТРОЙ ПРОЕКТ\" ЕООД, \"КАМЕКС - ТРАНС\" ЕООД","Object":"ЖИЛИЩНИ СГРАДИ С АТЕЛИЕТА, СКЛАДОВЕ, ГАРАЖИ И ПОДЗЕМНИ ГАРАЖИ - БЛОК \"А\" и БЛОК \"Б\"","Region":"Овча купел","Terrain":"БУЛ. ЦАР БОРИС III - II ЧАСТ","RegulationNeighbourhood":"231а","Upi":"VІІІ -788","Identifier":"68134.4340.788","Address":"гр. София, ул. \"Цар Борис ІІІ\" № 136-Б"},{"Number":"60/03.09.2018","Hash":"RxKbxBkYxX8=","DocumentTypeName":"Разрешение за строеж","Status":"Влязъл в сила","TakeEffectFilter":"\/Date(1537304400000)\/","TakeEffect":{"DateTime":"\/Date(1537304400000)\/","FilterText":null},"Issuer":"Главен архитект на СО - р-н \"Овча купел\"","Employer":"Атанас Симеоновски, Ивета Владимирова, Ивана Тошева, Николай Инджов","Object":"ЖИЛИЩНА СГРАДА С ПОДЗЕМНИ ГАРАЖИ","Region":"Овча купел","Terrain":"м. \"кв. Овча купел - актуализация\"","RegulationNeighbourhood":"37","Upi":"ХІІ-421 за ЖС","Identifier":"68134.4337.421","Address":"гр. София, ул. \"Бойчо Огнянов\""},{"Number":"97/03.09.2018","Hash":"qpeuAoyyYRo=","DocumentTypeName":"Разрешение за строеж","Status":"Влязъл в сила","TakeEffectFilter":"\/Date(1537477200000)\/","TakeEffect":{"DateTime":"\/Date(1537477200000)\/","FilterText":null},"Issuer":"Главен архитект на СО - р-н \"Лозенец\"","Employer":"Етажна собственост на жилищна сграда ","Object":"РЕМОНТ НА ПОКРИВ И ПОКРИВАНЕ НА ТЕРАСИ НА ЖИЛИЩНА СГРАДА","Region":"Лозенец","Terrain":"\"ВИТОША-ВЕЦ СИМЕОНОВО\"","RegulationNeighbourhood":"4","Upi":"XVII-23","Identifier":"Южна градска територия 4-та част","Address":"гр. София, ул. Яна Язова № 9"},{"Number":"96/03.09.2018","Hash":"kZlbmmG9Fo4=","DocumentTypeName":"Разрешение за строеж","Status":"Влязъл в сила","TakeEffectFilter":"\/Date(1537477200000)\/","TakeEffect":{"DateTime":"\/Date(1537477200000)\/","FilterText":null},"Issuer":"Главен архитект на СО - р-н \"Лозенец\"","Employer":"Етажна собственост на жилищна сграда","Object":"ВЪЗСТАНОВЯВАНЕ НА ПРОЕКТНИЯ КАПАЦИТЕТ НА ВЕРТИКАЛЕН НОСЕЩ ЕЛЕМЕНТ-ШАЙБА 3 В ЖИЛИЩНА СГРАДА","Region":"Лозенец","Terrain":"\"ВИТОША-ВЕЦ СИМЕОНОВО\"","RegulationNeighbourhood":"19","Upi":"X-1207,1208","Identifier":"68134.905.1208.1","Address":"гр. София, ул. Слав Караславов № 2"},{"Number":"212/31.08.2018","Hash":"snarXOXyD5k=","DocumentTypeName":"Разрешение за строеж","Status":"Влязъл в сила","TakeEffectFilter":"\/Date(1538686800000)\/","TakeEffect":{"DateTime":"\/Date(1538686800000)\/","FilterText":null},"Issuer":"Главен архитект на Столична община","Employer":"\"СОФИЯ ХОТЕЛ БАЛКАН\" АД","Object":"Преустройство и промяна на предназначението на част от помещението на седми етаж в сградата на София Хотел Балкан - от административни и обслужващи помещения и коридори в хотелски стаи, обслужващи помещения и коридори","Region":"Средец","Terrain":"м. „Център - Зона „А“ - юг“","RegulationNeighbourhood":"396","Upi":"I - \" За хотел\"","Identifier":"68134.100.6.1","Address":"гр. София, ул. пл.\"Света Неделя\" № 5"},{"Number":"59/31.08.2018","Hash":"UBaAnetJQTA=","DocumentTypeName":"Разрешение за строеж","Status":"Влязъл в сила","TakeEffectFilter":"\/Date(1537218000000)\/","TakeEffect":{"DateTime":"\/Date(1537218000000)\/","FilterText":null},"Issuer":"Главен архитект на СО - р-н \"Овча купел\"","Employer":"Росен Георгиев","Object":"ЕДНОФАМИЛНА ЖИЛИЩНА СГРАДА","Region":"Овча купел","Terrain":"С. МАЛО БУЧИНО","RegulationNeighbourhood":null,"Upi":null,"Identifier":"46721.3856.63","Address":"с. Мало Бучино"},{"Number":"58/30.08.2018","Hash":"e4ASSF_5j9A=","DocumentTypeName":"Разрешение за строеж","Status":"Влязъл в сила","TakeEffectFilter":"\/Date(1536958800000)\/","TakeEffect":{"DateTime":"\/Date(1536958800000)\/","FilterText":null},"Issuer":"Главен архитект на СО - р-н \"Овча купел\"","Employer":"ИВО ИВАНОВ","Object":"ПРЕУСТРОЙСТВО, ПРИСТРОЙКА КЪМ ЕДНОФАМИЛНА ЖИЛИЩНА СГРАДА И ДОПЪЛВАЩО ЗАСТРОЯВАНЕ ГАРАЖ СЪС СКЛАД","Region":"Овча купел","Terrain":"м. в.з.Горна баня","RegulationNeighbourhood":"44а","Upi":"V-247","Identifier":"68134.4329.247","Address":"гр. София, ул. \"745\" № 5"},{"Number":"47/30.08.2018","Hash":"NaQMqOBAj3c=","DocumentTypeName":"Разрешение за строеж","Status":"Влязъл в сила","TakeEffectFilter":"\/Date(1537304400000)\/","TakeEffect":{"DateTime":"\/Date(1537304400000)\/","FilterText":null},"Issuer":"Главен архитект на СО - р-н \"Слатина\"","Employer":"АГЕНЦИЯ РЕГУЛИРАНЕ","Object":"ОСНОВНО ОБНОВЯВАНЕ НА АДМИНИСТРАТИВНО ДЕЛОВА СГРАДА НА АГЕНЦИЯ ЗА ЯДРЕНО РЕГУЛИРАНЕ - НИСКА ЧАСТ с идентификатор 68134.703.1372.7","Region":"Слатина","Terrain":"\"Христо Смирненски-Слатина\"","RegulationNeighbourhood":"95в","Upi":"V-за ДКНТП","Identifier":"68134.703.1372","Address":"гр. София, ул. \"Шипченски проход\" № 69"},{"Number":"148/29.08.2018","Hash":"oQ6ixWilm5E=","DocumentTypeName":"Разрешение за строеж","Status":"Влязъл в сила","TakeEffectFilter":"\/Date(1538514000000)\/","TakeEffect":{"DateTime":"\/Date(1538514000000)\/","FilterText":null},"Issuer":"Главен архитект на СО - р-н \"Панчарево\"","Employer":"Венеция Цонковска","Object":"Пристройка и ремонт на съществуваща вилна сграда с идентификатор 04234.6906.648.2 със ЗП=76,96 кв.м ,от които 7,77 кв.м - пристройка и РЗП= 147,25 кв.м","Region":"Панчарево","Terrain":"В. З. МАЛИНОВА ДОЛИНА - ГЕРЕНА","RegulationNeighbourhood":"7","Upi":"II - 648","Identifier":"04234.6906.648","Address":"с. Бистрица"}],"Total":66292}